meshd_agent/__init__.py
meshd_agent/__main__.py
meshd_agent/core.py
meshd_agent/exceptions.py
meshd_agent/model.py
meshd_agent/settings.py
meshd_agent/util.py
meshd_agent-0.1.0.dist-info/WHEEL
meshd_agent-0.1.0.dist-info/METADATA
meshd_agent-0.1.0.dist-info/RECORD
