Metadata-Version: 2.1
Name: meshd-agent
Version: 0.1.0
Summary: The open source part of the Meshd Cloud.Remove the need to directly connect to your sources via the API and connect with this agent instead. https://meshd.cloud
Author: Toby Devlin
Author-email: hello@meshd.cloud
Requires-Python: >=3.10,<4.0
Classifier: Programming Language :: Python :: 3
Classifier: Programming Language :: Python :: 3.10
Classifier: Programming Language :: Python :: 3.11
Requires-Dist: fastapi-websocket-pubsub (>=0.3.1,<0.4.0)
Requires-Dist: pandas (>=1.5.2,<2.0.0)
Requires-Dist: pydantic (>=1.10.4,<2.0.0)
Requires-Dist: requests (>=2.28.2,<3.0.0)
Requires-Dist: sqlalchemy (==1.4.41)
